{
  "name": "いんせきの あな 地下1階",
  "description": "地下1階。じめじめと 熱く、道は せまい。さらに 下へ つづく ハシゴが ある。",
  "tileSize": 32,
  "width": 12,
  "height": 10,
  "layers": {
    "floor": [
      [
        81,
        81,
        81,
        81,
        81,
        81,
        81,
        81,
        81,
        81,
        81,
        81
      ],
      [
        81,
        80,
        80,
        80,
        80,
        80,
        80,
        80,
        80,
        80,
        80,
        81
      ],
      [
        81,
        80,
        82,
        80,
        80,
        80,
        80,
        80,
        80,
        80,
        80,
        81
      ],
      [
        81,
        80,
        80,
        80,
        80,
        81,
        81,
        80,
        80,
        80,
        80,
        81
      ],
      [
        81,
        80,
        80,
        80,
        80,
        80,
        80,
        80,
        80,
        80,
        80,
        81
      ],
      [
        81,
        80,
        80,
        80,
        80,
        80,
        80,
        80,
        81,
        80,
        80,
        81
      ],
      [
        81,
        80,
        80,
        80,
        81,
        80,
        80,
        80,
        80,
        80,
        80,
        81
      ],
      [
        81,
        80,
        80,
        80,
        80,
        80,
        80,
        80,
        80,
        80,
        80,
        81
      ],
      [
        81,
        80,
        80,
        80,
        80,
        80,
        80,
        80,
        80,
        82,
        80,
        81
      ],
      [
        81,
        81,
        81,
        81,
        81,
        81,
        81,
        81,
        81,
        81,
        81,
        81
      ]
    ],
    "collision": [
      [
        1,
        1,
        1,
        1,
        1,
        1,
        1,
        1,
        1,
        1,
        1,
        1
      ],
      [
        1,
        0,
        0,
        0,
        0,
        0,
        0,
        0,
        0,
        0,
        0,
        1
      ],
      [
        1,
        0,
        0,
        0,
        0,
        0,
        0,
        0,
        0,
        0,
        0,
        1
      ],
      [
        1,
        0,
        0,
        0,
        0,
        1,
        1,
        0,
        0,
        0,
        0,
        1
      ],
      [
        1,
        0,
        0,
        0,
        0,
        0,
        0,
        0,
        0,
        0,
        0,
        1
      ],
      [
        1,
        0,
        0,
        0,
        0,
        0,
        0,
        0,
        1,
        0,
        0,
        1
      ],
      [
        1,
        0,
        0,
        0,
        1,
        0,
        0,
        0,
        0,
        0,
        0,
        1
      ],
      [
        1,
        0,
        0,
        0,
        0,
        0,
        0,
        0,
        0,
        0,
        0,
        1
      ],
      [
        1,
        0,
        0,
        0,
        0,
        0,
        0,
        0,
        0,
        0,
        0,
        1
      ],
      [
        1,
        1,
        1,
        1,
        1,
        1,
        1,
        1,
        1,
        1,
        1,
        1
      ]
    ]
  },
  "tileTypes": {
    "80": {
      "name": "洞窟の床",
      "color": "#39313a",
      "walkable": true
    },
    "81": {
      "name": "岩壁",
      "color": "#1b151c",
      "walkable": false
    },
    "9": {
      "name": "でぐち",
      "color": "#60e8d8",
      "walkable": true
    },
    "82": {
      "name": "ハシゴ",
      "color": "#7a5a34",
      "walkable": true
    }
  },
  "playerStart": {
    "x": 2,
    "y": 3
  },
  "warps": [
    {
      "x": 2,
      "y": 2,
      "targetMap": "crater_cave",
      "targetX": 11,
      "targetY": 3
    },
    {
      "x": 9,
      "y": 8,
      "targetMap": "crater_cave_b2",
      "targetX": 2,
      "targetY": 3
    }
  ]
}